LICENSE
MANIFEST.in
README.md
setup.py
vaUserAgent/__init__.py
vaUserAgent/ua.py
vaUserAgent/ua.txt
vaUserAgent.egg-info/PKG-INFO
vaUserAgent.egg-info/SOURCES.txt
vaUserAgent.egg-info/dependency_links.txt
vaUserAgent.egg-info/top_level.txt