Metadata-Version: 1.0
Name: vaUserAgent
Version: 0.4.0
Summary: user agent random
Home-page: http://vvvv.io
Author: vavne
Author-email: UNKNOWN
License: LGPL
Platform: UNKNOWN
